MANIFEST.in
README.md
minidlnaindicator.desktop
minidlnaindicator.png
setup.py
minidlnaindicator/__init__.py
minidlnaindicator/constants.py
minidlnaindicator/fslistener.py
minidlnaindicator/fsmonitor.py
minidlnaindicator/indicator.py
minidlnaindicator/indicatorconfig.py
minidlnaindicator/minidlnaconfig.py
minidlnaindicator/processlistener.py
minidlnaindicator/processrunner.py
minidlnaindicator/proxy.py
minidlnaindicator/runner.py
minidlnaindicator/update_check_listener.py
minidlnaindicator/update_check_thread.py
minidlnaindicator/version.py
minidlnaindicator.egg-info/PKG-INFO
minidlnaindicator.egg-info/SOURCES.txt
minidlnaindicator.egg-info/dependency_links.txt
minidlnaindicator.egg-info/entry_points.txt
minidlnaindicator.egg-info/not-zip-safe
minidlnaindicator.egg-info/requires.txt
minidlnaindicator.egg-info/top_level.txt
minidlnaindicator/exceptions/__init__.py
minidlnaindicator/exceptions/alreadyrunning.py
minidlnaindicator/exceptions/processnotrunning.py
minidlnaindicator/exceptions/processstop.py
minidlnaindicator/icons/dlna_green_32.png
minidlnaindicator/icons/dlna_grey_32.png
minidlnaindicator/locale/es/LC_MESSAGES/minidlnaindicator.mo
minidlnaindicator/locale/es/LC_MESSAGES/minidlnaindicator.po
minidlnaindicator/ui/__init__.py
minidlnaindicator/ui/utils_ui.py